.gitignore
.pre-commit-config.yaml
.pylintrc
.readthedocs.yml
CODE_OF_CONDUCT.md
LICENSE
README.rst
README.rst.license
pyproject.toml
requirements.txt
setup.py
.github/workflows/build.yml
.github/workflows/release.yml
LICENSES/CC-BY-4.0.txt
LICENSES/MIT.txt
LICENSES/Unlicense.txt
adafruit_blinka_pyportal.egg-info/PKG-INFO
adafruit_blinka_pyportal.egg-info/SOURCES.txt
adafruit_blinka_pyportal.egg-info/dependency_links.txt
adafruit_blinka_pyportal.egg-info/requires.txt
adafruit_blinka_pyportal.egg-info/top_level.txt
adafruit_pyportal/__init__.py
adafruit_pyportal/graphics.py
adafruit_pyportal/network.py
adafruit_pyportal/peripherals.py
adafruit_pyportal/wifi.py
docs/api.rst
docs/api.rst.license
docs/conf.py
docs/examples.rst
docs/examples.rst.license
docs/index.rst
docs/index.rst.license
docs/_static/favicon.ico
docs/_static/favicon.ico.license
examples/adafruit_blinka_pyportal_bitcoin.py
examples/adafruit_blinka_pyportal_discord.py
examples/adafruit_blinka_pyportal_nasa.py
examples/adafruit_blinka_pyportal_openweather.py
examples/adafruit_blinka_pyportal_openweather_graphics.py
examples/adafruit_blinka_pyportal_quote.py