Metadata-Version: 2.1
Name: adafruit-blinka-pyportal
Version: 2.0.0
Summary: A port of the PyPortal library intended to run on Blinka in CPython.
Home-page: https://github.com/adafruit/Adafruit_Blinka_PyPortal
Author: Adafruit Industries
Author-email: circuitpython@adafruit.com
License: MIT
Keywords: adafruit blinka circuitpython micropython pyportal displayio touchscreen neetwork
Platform: UNKNOWN
Classifier: Development Status :: 3 - Alpha
Classifier: Intended Audience :: Developers
Classifier: Topic :: Software Development :: Libraries
Classifier: Topic :: System :: Hardware
Classifier: License :: OSI Approved :: MIT License
Classifier: Programming Language :: Python :: 3
Classifier: Programming Language :: Python :: 3.4
Classifier: Programming Language :: Python :: 3.5
